[
  {
    "id": "yjdz84yyoeql5ag8j8f",
    "timestamp": 1657163291487,
    "productos": [
      {
        "id": "5t3lk8p8fkvl5ain2h3",
        "timestamp": 1657167328839,
        "nombre": "Coca",
        "descripcion": "Coca xd",
        "codigo": "p001",
        "foto": "foto",
        "precio": 10,
        "stock": 10
      }
    ]
  },
  {
    "id": "5cy15tl3ssfl5ai5afi",
    "timestamp": 1657166499342,
    "productos": [
      {
        "id": "9a2hjceufm6l5ads1u6",
        "timestamp": 1657159163214,
        "nombre": "Pepsi",
        "descripcion": "Pepsi xd",
        "codigo": "p001",
        "foto": "foto",
        "precio": 10,
        "stock": 10
      }
    ]
  },
  {
    "id": "uk7a3g4c4dl5ai5chc",
    "timestamp": 1657166502000,
    "productos": [
      {
        "id": "9a2hjceufm6l5ads1u6",
        "timestamp": 1657159163214,
        "nombre": "Pepsi",
        "descripcion": "Pepsi xd",
        "codigo": "p001",
        "foto": "foto",
        "precio": 10,
        "stock": 10
      }
    ]
  }
]